setup.py
ondelta/__init__.py
ondelta/models.py
ondelta/signals.py
ondelta.egg-info/PKG-INFO
ondelta.egg-info/SOURCES.txt
ondelta.egg-info/dependency_links.txt
ondelta.egg-info/requires.txt
ondelta.egg-info/top_level.txt