Metadata-Version: 1.1
Name: ondelta
Version: 0.6.0
Summary: A mixin that allows models to register methods that are notified when their values change,or register a method that is notified of all changes. Basically, OnDeltaMixin implementsthe observer pattern.
Home-page: https://github.com/adamhaney/django-ondelta
Author: Adam Haney
Author-email: adam.haney@getbellhops.com
License: LGPL
Keywords: Django,observer
Platform: UNKNOWN
Classifier: Development Status :: 4 - Beta
Classifier: Environment :: Web Environment
Classifier: Framework :: Django
Classifier: Intended Audience :: Developers
Classifier: License :: OSI Approved :: MIT License
Classifier: Operating System :: OS Independent
Classifier: Programming Language :: Python
Classifier: Programming Language :: Python :: 2
Classifier: Programming Language :: Python :: 2.7
Classifier: Programming Language :: Python :: 3
Classifier: Programming Language :: Python :: 3.3
Classifier: Programming Language :: Python :: 3.4
Classifier: Programming Language :: Python :: Implementation :: CPython
Classifier: Programming Language :: Python :: Implementation :: PyPy
Classifier: Topic :: Internet :: WWW/HTTP
